cgtypes.cpython-311-darwin.so
pycgtypes/__init__.py
pycgtypes/mat3.py
pycgtypes/mat4.py
pycgtypes/quat.py
pycgtypes/vec3.py
pycgtypes/vec4.py
cgkit1-1.2.8.dist-info/METADATA
cgkit1-1.2.8.dist-info/WHEEL
cgkit1-1.2.8.dist-info/top_level.txt
cgkit1-1.2.8.dist-info/RECORD
