Metadata-Version: 2.1
Name: cgkit1
Version: 1.2.8
Summary: Python Computer Graphics Kit v1
Author-email: Matthias Bass <baas@ira.uka.de>
Maintainer-email: Andrew Straw <strawman@astraw.com>
License: Copyright (c) 2002, Matthias Baas
Project-URL: homepage, https://github.com/strawlab/cgkit1
Requires-Python: >=3.7
